{
  "id": 225,
  "title (japanese)": "ハピネスパッケージガチャ",
  "release_date": "7/29/2022, 8:00:00 PM",
  "type": "gift",
  "gacha_rate_index": 2,
  "featured_cards": [
    {
      "card_id": "398",
      "normal_rate": 0.021,
      "guaranteed_rate": 0.694
    },
    {
      "card_id": "374",
      "normal_rate": 0.021,
      "guaranteed_rate": 0.694
    },
    {
      "card_id": "380",
      "normal_rate": 0.021,
      "guaranteed_rate": 0.694
    },
    {
      "card_id": "410",
      "normal_rate": 0.021,
      "guaranteed_rate": 0.694
    },
    {
      "card_id": "392",
      "normal_rate": 0.021,
      "guaranteed_rate": 0.694
    },
    {
      "card_id": "320",
      "normal_rate": 0.021,
      "guaranteed_rate": 0.694
    }
  ]
}