{
  "id": "971",
  "character": "Kagamine Rin",
  "character (japanese)": "鏡音 リン",
  "english name": "Carrying the Feelings I Want to Deliver!",
  "japanese name": "届けたい気持ちをのせて！",
  "skill name (japanese)": "やっぱりアイドルっていいな！",
  "skill name (english)": "Idols Really Are Nice!",
  "skill effect (japanese)": "ライフが400回復し、5秒間 スコアが60%UPする",
  "skill effect (english)": "Recover 400 life and 60% score boost for 5 seconds.",
  "talent (max)": 28434,
  "gacha phrase": "こういうポーズはどうかな！？",
  "unit": "VIRTUAL SINGER",
  "support unit": "MORE MORE JUMP!",
  "attribute": "Cute",
  "rarity": 3,
  "status": "Permanent"
}