{
  "id": "702",
  "character": "MEIKO",
  "character (japanese)": "MEIKO",
  "english name": "Storyteller of Happiness",
  "japanese name": "幸福の語り手",
  "skill name (japanese)": "きらきらな夢を見守って",
  "skill name (english)": "Watching Over the Dreams That Sparkle Brightly",
  "skill effect (japanese)": "5秒間 スコアが120%UPする",
  "skill effect (english)": "120% score boost for 5 seconds.",
  "talent (max)": 31737,
  "gacha phrase": "ずうっと仲良くショーを続けましたとさ",
  "unit": "VIRTUAL SINGER",
  "support unit": "Wonderlands×Showtime",
  "attribute": "Happy",
  "rarity": 4,
  "status": "Permanent"
}