{
  "id": "1109",
  "character": "Yoisaki Kanade",
  "character (japanese)": "宵崎 奏",
  "english name": "Happy Birthday!! 2025 (Kanade)",
  "japanese name": "Happy Birthday！！2025",
  "skill name (japanese)": "友人達に囲まれて",
  "skill name (english)": "Surrounded by Friends",
  "skill effect (japanese)": "ライフが850回復し、5秒間 PERFECTのときのみスコアが80%UPする",
  "skill effect (english)": "Recover 850 life and 80% score boost for 5 seconds for PERFECTs only.",
  "talent (max)": 30618,
  "gacha phrase": "こんなに賑やかな誕生日が来るなんて",
  "unit": "25-ji, Nightcord de.",
  "support unit": null,
  "attribute": "Cute",
  "rarity": "Birthday",
  "status": "Birthday limited"
}