{
  "id": "489",
  "character": "Shinonome Ena",
  "character (japanese)": "東雲 絵名",
  "english name": "Because I Want to Create Something Good",
  "japanese name": "いいものを作りたいから",
  "skill name (japanese)": "KからのDM",
  "skill name (english)": "A DM From K",
  "skill effect (japanese)": "6.5秒間 GOOD以上がPERFECTになり、5秒間 スコアが60％UPする",
  "skill effect (english)": "All GOODs and higher will become PERFECTs for 6.5 seconds and 60% score boost for 5 seconds.",
  "talent (max)": 28439,
  "gacha phrase": "じゃあ、ちょっとやってみよっか",
  "unit": "25-ji, Nightcord de.",
  "support unit": null,
  "attribute": "Mysterious",
  "rarity": 3,
  "status": "Permanent"
}