{
  "id": "743",
  "character": "Akiyama Mizuki",
  "character (japanese)": "暁山 瑞希",
  "english name": "Brand New Style (Mizuki 2☆)",
  "japanese name": "Brand New Style",
  "skill name (japanese)": "友情のキューピッド？",
  "skill name (english)": "Cupid of friendship?",
  "skill effect (japanese)": "6秒間 GREATがPERFECTになり、5秒間 スコアが30％UPする",
  "skill effect (english)": "All GREATs and higher will become PERFECTs for 6.0 seconds and 30% score boost for 5 seconds.",
  "talent (max)": 19986,
  "gacha phrase": null,
  "unit": "25-ji, Nightcord de.",
  "support unit": null,
  "attribute": "Cute",
  "rarity": 2,
  "status": "Permanent"
}