{
  "id": "22",
  "character": "Kiritani Haruka",
  "character (japanese)": "桐谷 遥",
  "english name": "MORE MORE JUMP! (Haruka 2☆)",
  "japanese name": "MORE MORE JUMP！",
  "skill name (japanese)": "全部、２個ずつください",
  "skill name (english)": "Two of Each, Please",
  "skill effect (japanese)": "5秒間 スコアが50%UPする",
  "skill effect (english)": "50% score boost for 5 seconds.",
  "talent (max)": 16969,
  "gacha phrase": null,
  "unit": "MORE MORE JUMP!",
  "support unit": null,
  "attribute": "Pure",
  "rarity": 2,
  "status": "Permanent"
}