{
  "id": "806",
  "character": "Shinonome Ena",
  "character (japanese)": "東雲 絵名",
  "english name": "Feat. Kuromi",
  "japanese name": "feat.クロミ",
  "skill name (japanese)": "贅沢者の集まり？",
  "skill name (english)": "A Gathering of Fancy People?",
  "skill effect (japanese)": "ライフが500回復し、5秒間 スコアが100%UPする",
  "skill effect (english)": "Recover 500 life and 100% score boost for 5 seconds.",
  "talent (max)": 32044,
  "gacha phrase": "もう、こんなのいつの間に撮ったの？",
  "unit": "25-ji, Nightcord de.",
  "support unit": null,
  "attribute": "Cool",
  "rarity": 4,
  "status": "Limited"
}