{
  "id": "77",
  "character": "Akiyama Mizuki",
  "character (japanese)": "暁山 瑞希",
  "english name": "A Free Spirit in Love With Everything Cute",
  "japanese name": "『カワイイ』にこだわる自由人",
  "skill name (japanese)": "猫舌だから♪",
  "skill name (english)": "Because Hot Food Is No Good ♪",
  "skill effect (japanese)": "5秒間 スコアが40%UPする",
  "skill effect (english)": "40% score boost for 5 seconds.",
  "talent (max)": 7577,
  "gacha phrase": null,
  "unit": "25-ji, Nightcord de.",
  "support unit": null,
  "attribute": "Cute",
  "rarity": 1,
  "status": "Permanent"
}