{
  "id": "301",
  "character": "Kamishiro Rui",
  "character (japanese)": "神代 類",
  "english name": "Longing for the Old Days",
  "japanese name": "在りし日の憧憬",
  "skill name (japanese)": "ようこそ僕の家へ！",
  "skill name (english)": "Welcome to My Residence!",
  "skill effect (japanese)": "7秒間 BAD以上がPERFECTになり、5秒間 スコアが100％UPする",
  "skill effect (english)": "All BADs and higher will become PERFECTs for 7.0 seconds and 100% score boost for 5 seconds.",
  "talent (max)": 32044,
  "gacha phrase": "正解なんてなくて、とっても自由なんだ",
  "unit": "Wonderlands×Showtime",
  "support unit": null,
  "attribute": "Happy",
  "rarity": 4,
  "status": "Permanent"
}