{
  "id": "925",
  "character": "Kagamine Rin",
  "character (japanese)": "鏡音 リン",
  "english name": "A Mysterious Path Discovered!?",
  "japanese name": "謎の道、発見！？",
  "skill name (japanese)": "花畑の間違い探し？",
  "skill name (english)": "A Game of Spot the Difference in the Flower Garden?",
  "skill effect (japanese)": "5秒間 スコアが50%UPする",
  "skill effect (english)": "50% score boost for 5 seconds.",
  "talent (max)": 19823,
  "gacha phrase": null,
  "unit": "VIRTUAL SINGER",
  "support unit": "MORE MORE JUMP!",
  "attribute": "Cute",
  "rarity": 2,
  "status": "Permanent"
}