{
  "id": "574",
  "character": "Tenma Tsukasa",
  "character (japanese)": "天馬 司",
  "english name": "Never Give Up",
  "japanese name": "ネバーギブアップ",
  "skill name (japanese)": "学びのワークショップ",
  "skill name (english)": "Workshop Studies",
  "skill effect (japanese)": "ライフが400回復し、5秒間 スコアが60%UPする",
  "skill effect (english)": "Recover 400 life and 60% score boost for 5 seconds.",
  "talent (max)": 28439,
  "gacha phrase": "もう１回、お願いします！",
  "unit": "Wonderlands×Showtime",
  "support unit": null,
  "attribute": "Pure",
  "rarity": 3,
  "status": "Permanent"
}